COPYING.txt
README.rst
ebf.py
setup.py
ebfpy.egg-info/PKG-INFO
ebfpy.egg-info/SOURCES.txt
ebfpy.egg-info/dependency_links.txt
ebfpy.egg-info/top_level.txt
scripts/ebftk