Metadata-Version: 2.4
Name: ebfpy
Version: 0.0.40
Summary: a module to read and write .ebf files (efficient and easy to use binary format) for python 2 and 3 
Author: Sanjib Sharma
Author-email: bugsanjib@gmail.com
Platform: any
Classifier: Programming Language :: Python
Classifier: Development Status :: 4 - Beta
Classifier: Intended Audience :: Developers
Classifier: Intended Audience :: Science/Research
Classifier: License :: OSI Approved :: BSD License
Classifier: Operating System :: OS Independent
Classifier: Topic :: Software Development :: Libraries :: Python Modules
Classifier: Topic :: Scientific/Engineering
License-File: COPYING.txt
Dynamic: author
Dynamic: author-email
Dynamic: classifier
Dynamic: description
Dynamic: description-content-type
Dynamic: license-file
Dynamic: platform
Dynamic: summary
